foldertree/__init__.py
foldertree/cli.py
foldertree/core.py
treescaffold-1.4.4.dist-info/licenses/LICENSE
treescaffold-1.4.4.dist-info/METADATA
treescaffold-1.4.4.dist-info/WHEEL
treescaffold-1.4.4.dist-info/entry_points.txt
treescaffold-1.4.4.dist-info/top_level.txt
treescaffold-1.4.4.dist-info/RECORD
