Metadata-Version: 2.4
Name: treescaffold
Version: 1.4.4
Summary: Generate folder structures from various input formats (tree, YAML, simple indentation)
Home-page: https://github.com/sree-sphere/foldertree
Author: Sreeprad
Author-email: Sreeprad <sreeprad99@gmail.com>
License: MIT
Project-URL: Homepage, https://github.com/sree-sphere/foldertree
Project-URL: Documentation, https://github.com/sree-sphere/foldertree#readme
Project-URL: Repository, https://github.com/sree-sphere/foldertree
Project-URL: Issues, https://github.com/sree-sphere/foldertree/issues
Keywords: folder,directory,structure,generator,tree,scaffold
Classifier: Development Status :: 5 - Production/Stable
Classifier: Intended Audience :: Developers
Classifier: License :: OSI Approved :: MIT License
Classifier: Operating System :: OS Independent
Classifier: Programming Language :: Python :: 3
Classifier: Programming Language :: Python :: 3.7
Classifier: Programming Language :: Python :: 3.8
Classifier: Programming Language :: Python :: 3.9
Classifier: Programming Language :: Python :: 3.10
Classifier: Programming Language :: Python :: 3.11
Classifier: Programming Language :: Python :: 3.12
Classifier: Topic :: Software Development :: Code Generators
Classifier: Topic :: System :: Filesystems
Classifier: Topic :: Utilities
Requires-Python: >=3.7
License-File: LICENSE
Requires-Dist: PyYAML>=5.4.0
Provides-Extra: dev
Requires-Dist: pytest>=6.0; extra == "dev"
Requires-Dist: pytest-cov>=2.0; extra == "dev"
Requires-Dist: black>=22.0; extra == "dev"
Requires-Dist: flake8>=4.0; extra == "dev"
Requires-Dist: mypy>=0.900; extra == "dev"
Dynamic: author
Dynamic: home-page
Dynamic: license-file
Dynamic: requires-python
